LICENSE
MANIFEST.in
NOTICE
README.md
requirements.txt
setup.cfg
setup.py
compiler/__init__.py
compiler/api/__init__.py
compiler/api/compiler.py
compiler/api/source/auth_key.tl
compiler/api/source/main_api.tl
compiler/api/source/sys_msgs.tl
compiler/api/template/combinator.txt
compiler/api/template/type.txt
compiler/errors/__init__.py
compiler/errors/compiler.py
compiler/errors/sort.py
compiler/errors/source/303_SEE_OTHER.tsv
compiler/errors/source/400_BAD_REQUEST.tsv
compiler/errors/source/401_UNAUTHORIZED.tsv
compiler/errors/source/403_FORBIDDEN.tsv
compiler/errors/source/406_NOT_ACCEPTABLE.tsv
compiler/errors/source/420_FLOOD.tsv
compiler/errors/source/500_INTERNAL_SERVER_ERROR.tsv
compiler/errors/source/503_SERVICE_UNAVAILABLE.tsv
compiler/errors/template/class.txt
compiler/errors/template/sub_class.txt
geezlibs/__init__.py
geezlibs/assistant.py
geezlibs/client.py
geezlibs/dispatcher.py
geezlibs/emoji.py
geezlibs/file_id.py
geezlibs/filters.py
geezlibs/mime_types.py
geezlibs/py.typed
geezlibs/sync.py
geezlibs/utils.py
geezlibs/connection/__init__.py
geezlibs/connection/connection.py
geezlibs/connection/transport/__init__.py
geezlibs/connection/transport/tcp/__init__.py
geezlibs/connection/transport/tcp/tcp.py
geezlibs/connection/transport/tcp/tcp_abridged.py
geezlibs/connection/transport/tcp/tcp_abridged_o.py
geezlibs/connection/transport/tcp/tcp_full.py
geezlibs/connection/transport/tcp/tcp_intermediate.py
geezlibs/connection/transport/tcp/tcp_intermediate_o.py
geezlibs/crypto/__init__.py
geezlibs/crypto/aes.py
geezlibs/crypto/mtproto.py
geezlibs/crypto/prime.py
geezlibs/crypto/rsa.py
geezlibs/enums/__init__.py
geezlibs/enums/auto_name.py
geezlibs/enums/chat_action.py
geezlibs/enums/chat_event_action.py
geezlibs/enums/chat_member_status.py
geezlibs/enums/chat_members_filter.py
geezlibs/enums/chat_type.py
geezlibs/enums/message_entity_type.py
geezlibs/enums/message_media_type.py
geezlibs/enums/message_service_type.py
geezlibs/enums/messages_filter.py
melvant.egg-info/PKG-INFO
melvant.egg-info/SOURCES.txt
melvant.egg-info/dependency_links.txt
melvant.egg-info/not-zip-safe
melvant.egg-info/requires.txt
melvant.egg-info/top_level.txt
