Metadata-Version: 2.1
Name: melvant
Version: 0.0.5
Summary: geezlibs - Telegram MTProto API Client Library for Python.
Home-page: https://github.com/hitokizzy/geezlibs
Author: AyiinXd
Author-email: Ayin@gmail.com
License: GNU Lesser General Public License v3.0 (LGPL-3.0)
Project-URL: Bug Tracker, https://github.com/hitokizzy/geezlibs/issues
Project-URL: Documentation, https://geezlibs.tech
Project-URL: Source Code, https://github.com/hitokizzy/geezlibs
Classifier: Programming Language :: Python :: 3
Classifier: Programming Language :: Python :: 3.8
Classifier: Programming Language :: Python :: 3.9
Classifier: Programming Language :: Python :: 3.10
Classifier: License :: OSI Approved :: GNU General Public License v3 (GPLv3)
Classifier: Operating System :: OS Independent
Requires-Python: ~=3.7
License-File: LICENSE
License-File: NOTICE
